<?xml version="1.0" encoding="UTF-8"?>
<?xml-stylesheet href="indent.css"?>
<list>
  <li class="book_head" image="images/JHN.jpg" ref="JHN"></li>
  <list class="sub1">
    <li class="li1" ref="JHN 1">Introduction (JHN 1)</li>
    <list class="sub2">
    <li class="li2" ref="JHN 1:1-18">In the Beginning was the Word (JHN )</li>
    <li class="li2" ref="JHN 1:19-51">7 titles of Jesus (JHN )</li>
  </list>
  </list>
<list class="sub1">
  <li class="li1" ref="JHN 2-10">Miraculous Signs &amp; Controversies (JHN )</li>
  <list class="sub2">
    <li class="li2" ref="JHN 2-4">Four Jewish Institutions (JHN )</li>
    <list class="sub3">
    <li class="li3" ref="JHN 2a">A Wedding (JHN )</li>
    <li class="li3" ref="JHN 2b">The Temple (JHN )</li>
    <li class="li3" ref="JHN 3">A Rabbi (JHN )</li>
    <li class="li3" ref="JHN 4">A Sacred Well (JHN )</li>
  </list>
  <li class="li2" ref="JHN 5-10">Four Jewish Feasts (JHN )</li>
   <list class="sub3">
    <li class="li3" ref="JHN 5">Sabbath (JHN )</li>
    <li class="li3" ref="JHN 6">Passover (JHN )</li>
    <li class="li3" ref="JHN 7-10a">Tabernacles (JHN )</li>
     <li class="li3" ref="JHN 10b">Hanukkah (JHN )</li>
  </list>
  </list>
</list>
<list class="sub1">
    <li class="li1" ref="JHN 11-12">Raising Lazarus (JHN )</li>
</list>
<list class="sub1">
  <li class="li1" ref="JHN 13-17">Jesus' Final Words (JHN )</li>
  <list class="sub2">
    <li class="li2" ref="JHN 13">Jesus Washes His Disciples Feet &amp; Gives His Great Command (JHN )</li>
    <li class="li2" ref="JHN 14-17">Jesus' Speech &amp; Prayer (JHN )</li>
  </list>
</list>
<list class="sub1">
  <li class="li1" ref="JHN 18-20">Jesus' Death &amp; Resurrection (JHN )</li>
  <list class="sub2">
    <li class="li2" ref="JHN 18a">Jesus' Arrest (JHN )</li>
    <li class="li2" ref="JHN 18b-19">Jesus' Crucifixion (JHN )</li>
     <li class="li2" ref="JHN 20">The Resurrection (JHN )</li>
  </list>
</list>
<list class="sub1">
    <li class="li1" ref="JHN 21">Epilogue (JHN )</li>
  </list>

</list>
